arua/__init__.py
arua/__main__.py
arua/app.py
arua/calculator.py
arua/compress_cli.py
arua/compression.py
arua/rands.py
arua/templates.py
arua/compression/__init__.py
arua/compression/core.py
arua/compression/flow.py
arua/compression/grain.py
arua/compression/helpers.py
arua/compression/lz77.py
arua/compression/orca_integration.py
arua/compression/sa_json.py
arua/compression/semantic.py
arua/compression/semantic_accelerator.py
arua/compression/semantic_aura.py
arua/compression/semantic_cache.py
arua/compression/semantic_combo.py
arua/compression/semantic_context.py
arua/compression/semantic_derivative.py
arua/compression/semantic_entropy.py
arua/compression/semantic_fastpath.py
arua/compression/semantic_grain.py
arua/compression/semantic_hash.py
arua/compression/semantic_index.py
arua/compression/semantic_integrator.py
arua/compression/semantic_interplay.py
arua/compression/semantic_joint.py
arua/compression/semantic_key.py
arua/compression/semantic_learned.py
arua/compression/semantic_memory.py
arua/compression/semantic_node.py
arua/compression/semantic_orchestration.py
arua/compression/semantic_pattern.py
arua/compression/semantic_plans.py
arua/compression/semantic_quantization.py
arua/compression/semantic_resolver.py
arua/compression/semantic_routing.py
arua/compression/semantic_sa.py
arua/compression/semantic_sb.py
arua/compression/semantic_store.py
arua/compression/semantic_stream.py
arua/compression/semantic_table.py
arua/compression/semantic_unique.py
arua/compression/semantic_vector.py
arua/compression/semantic_x.py
arua/compression/semantic_yield.py
arua/compression/semantic_z.py
optimizations/jetson/bench_aura_ai.py
optimizations/jetson/bench_core_ai.py
optimizations/jetson/bench_gpu.py
optimizations/jetson/setup.py
optimizations/jetson/trt_integration.py
optimizations/rtx/bench_gpu.py
optimizations/rtx/trt_integration.py
aura_s-0.1.0.dist-info/METADATA
aura_s-0.1.0.dist-info/WHEEL
aura_s-0.1.0.dist-info/top_level.txt
aura_s-0.1.0.dist-info/RECORD
